channels_demultiplexer/__init__.py
channels_demultiplexer/apps.py
channels_demultiplexer/conf.py
channels_demultiplexer/demultiplexer.py
channels_demultiplexer/queue.py
tests/__init__.py
tests/settings.py
tests/tests.py
tests/urls.py
channels_demultiplexer-2.2.0.dist-info/LICENSE
channels_demultiplexer-2.2.0.dist-info/METADATA
channels_demultiplexer-2.2.0.dist-info/WHEEL
channels_demultiplexer-2.2.0.dist-info/top_level.txt
channels_demultiplexer-2.2.0.dist-info/RECORD
