Metadata-Version: 2.1
Name: channels-demultiplexer
Version: 2.2.0
Summary: Demultiplexer for Django Channels
Home-page: https://github.com/csdenboer/channels-demultiplexer
Author: Christian den Boer
License: MIT
Project-URL: Documentation, https://channels-demultiplexer.readthedocs.io/
Project-URL: Source, https://github.com/csdenboer/channels-demultiplexer
Project-URL: Tracker, https://github.com/csdenboer/channels-demultiplexer/issues
Platform: UNKNOWN
Classifier: Development Status :: 5 - Production/Stable
Classifier: Environment :: Web Environment
Classifier: Framework :: Django
Classifier: Framework :: Django :: 2.2
Classifier: Framework :: Django :: 3.0
Classifier: Framework :: Django :: 3.1
Classifier: Programming Language :: Python
Classifier: Programming Language :: Python :: 3
Classifier: Programming Language :: Python :: 3.6
Classifier: Programming Language :: Python :: 3.7
Classifier: Programming Language :: Python :: 3.8
Classifier: Programming Language :: Python :: 3.9
Classifier: License :: OSI Approved :: MIT License
Classifier: Operating System :: OS Independent
Classifier: Topic :: Internet :: WWW/HTTP
Classifier: Topic :: Software Development :: Libraries :: Python Modules
Requires-Python: >=3.6
Requires-Dist: channels (>=3.0.0)
Requires-Dist: django-appconf (>=1.0.4)
